{"deploy-colab.md":"DdErVy_2","deploy-local.md":"DAM4FgSP","empty.md":"CfjMt2ar","feature-base.md":"VV2cFkNE","feature-draft.md":"DSzvBSxh","feature-transcribe.md":"BVJ6Cpvo","feature-translation.md":"D1WK6XZ8","feature-tts.md":"jQlBqt8d","gradio.md":"CTNAowm7","help-glossary.md":"DMYbdF3K","help-model.md":"BeY1Xhr9","index.md":"O2hRbWhP","maskpainter.md":"iXvRdYqh","preparation.md":"Cv2zV29N","vitepress.md":"DF9muX0i","what-is-creatorbox.md":"BaH_7kk1","zh_deploy-colab.md":"g7ESClu4","zh_deploy-local.md":"BzoxAnbQ","zh_empty.md":"B6UEEMxX","zh_feature-base.md":"WfmqUDXW","zh_feature-draft.md":"BqJ_U3wW","zh_feature-transcribe.md":"5boc0dAZ","zh_feature-translation.md":"BrSgOaIC","zh_feature-tts.md":"DnYeLeY4","zh_gradio.md":"BaGY1f0r","zh_help-glossary.md":"BPulECVu","zh_help-model.md":"DqBsuDx2","zh_index.md":"BiyEv2h6","zh_maskpainter.md":"r4Inw1wE","zh_preparation.md":"2PfJafCb","zh_vitepress.md":"DVqPNV8y","zh_what-is-creatorbox.md":"CKfPxe-8"}
