{"deploy-colab.md":"-JxKnXlF","deploy-local.md":"Bpy6YHo9","empty.md":"BDgV310c","feature-draft.md":"D7hTqHUm","feature-dubbing.md":"Ct6Yybwj","feature-scene.md":"DHeUYeT7","feature-transcribe.md":"D5PJA4bE","feature-translation.md":"OpD8e7HF","gradio.md":"BCPdRh1n","help-glossary.md":"BzvRQnrk","help-model.md":"CqpJrRxj","index.md":"xOg5tq8L","preparation.md":"B6vIY6CX","vitepress.md":"Cd0MMNwv","what-is-creatorbox.md":"DL-MOkcb","zh_deploy-colab.md":"BfulQIVw","zh_deploy-local.md":"DHUQLMu4","zh_empty.md":"B6UEEMxX","zh_feature-draft.md":"CZsV7VXA","zh_feature-dubbing.md":"ry7ToNLi","zh_feature-scene.md":"BolLuMWO","zh_feature-transcribe.md":"DsYQbD_c","zh_feature-translation.md":"CfvLuzDK","zh_gradio.md":"BHKztYdU","zh_help-glossary.md":"DWhs4OYJ","zh_help-model.md":"CnjQuJoD","zh_index.md":"D0DZIafg","zh_preparation.md":"mki06scZ","zh_vitepress.md":"BLvKGSxm","zh_what-is-creatorbox.md":"CzLm6JGk"}
