{"common_empty.md":"CzxkC0Dt","common_force.md":"DpxE_6_w","common_startup.md":"H8yelwzG","common_uv.md":"CXgYN_jy","common_zh_empty.md":"ChMhrMyt","common_zh_force.md":"CbHPLI1j","common_zh_uv.md":"fMR9ASLA","component_gmt.md":"nVx6r-46","component_index.md":"CwvmBPZ6","component_vmi.md":"Dr3mHdRA","deploy-colab.md":"ieErhTf4","deploy-local.md":"Btyixed3","experimental_capcut.md":"BDfP9Sl1","extension_cosyvoice.md":"CymU5vWo","extension_dubbing_index.md":"CtJExwTp","extension_dubbing_scene.md":"DoOES64K","extension_dubbing_transcribe.md":"C3VT2mU2","extension_dubbing_translation.md":"DGXiqvdg","extension_dubbing_tts.md":"CZdjzhFf","extension_gptsovits.md":"Du6JEDMX","extension_index.md":"DgnzJPeT","extension_indextts.md":"BpJrBKkk","extension_iopaint.md":"DxdHm4fx","extension_sd.md":"p_-yeSm9","extension_voxcpm.md":"cmeZA0jB","help_faq.md":"CHNTW35W","help_justmysocks.md":"CVEROd3X","help_output.md":"Bu5Va0Wn","help_terminal.md":"DMyJoX1R","index.md":"DYS7wwrw","preparation.md":"CG0Phhvb","team.md":"CQu_r-nf","tools.md":"CrD6GBYq","vitepress.md":"DVUspUXy","what-is-creatorbox.md":"BkkeRIWK","zh_component_gmt.md":"CQ--EgRg","zh_component_index.md":"LGootDqo","zh_component_vmi.md":"CstW5FAw","zh_deploy-colab.md":"BY54HPV5","zh_deploy-local.md":"DtbQeQuh","zh_experimental_capcut.md":"DqebRTKz","zh_extension_cosyvoice.md":"BX0dhJyB","zh_extension_dubbing_index.md":"B-oLPYvq","zh_extension_dubbing_scene.md":"DjpLVXmQ","zh_extension_dubbing_transcribe.md":"EpypX1Yh","zh_extension_dubbing_translation.md":"CFHilEqQ","zh_extension_dubbing_tts.md":"D1wuhX-j","zh_extension_gptsovits.md":"CToBpngC","zh_extension_index.md":"B1vbz2-O","zh_extension_indextts.md":"dPmPHVsO","zh_extension_iopaint.md":"DufntjgG","zh_extension_sd.md":"LmQPZwXD","zh_extension_voxcpm.md":"Crdf6yW9","zh_help_faq.md":"BMNA3ts3","zh_help_justmysocks.md":"D6uwEFta","zh_help_output.md":"pDsquLCh","zh_help_terminal.md":"B9c0bEaL","zh_index.md":"DvhXOa_U","zh_preparation.md":"CtRFffq7","zh_team.md":"xQnH_1P9","zh_tools.md":"CwoiSNRZ","zh_vitepress.md":"Ceb3pgy4","zh_what-is-creatorbox.md":"C2i6j-6_"}
